{
    "Api": {
        "Methods": [
            {
                "Params": [
                    "{cnf:cnf}"
                ],
                "Path": "/",
                "Return": "{interpretation:interpretation}",
                "Type": "Post"
            }
        ],
        "Port": "8080",
        "Type": "Rest"
    },
    "Container": {
        "Arch": "x86",
        "Entrypoint": "python3 /Solvers-frontier/start.py",
        "Envs": null,
        "Filesys": null
    },
    "Contract": null,
    "Dependency": null,
    "Ledger": null,
    "Tensor": null
}